dash_shap_components/ForceArrayPlot.py
dash_shap_components/ForcePlot.py
dash_shap_components/__init__.py
dash_shap_components/_imports_.py
dash_shap_components/dash_shap_components.min.js
dash_shap_components/dash_shap_components.min.js.map
dash_shap_components/metadata.json
dash_shap_components/package-info.json
dash_shap_components-0.0.2.dist-info/LICENSE
dash_shap_components-0.0.2.dist-info/METADATA
dash_shap_components-0.0.2.dist-info/WHEEL
dash_shap_components-0.0.2.dist-info/top_level.txt
dash_shap_components-0.0.2.dist-info/RECORD
